{
  "genre": "entertainment",
  "topic": "tv_shows",
  "quizName": "sitcom_classics",
  "difficulty": 2,
  "pointsMultiplier": 1.0,
  "questions": [
    {
      "question": "In 'Friends', what is Phoebe's most famous song?",
      "answers": [
        "Smelly Cat",
        "Two of Them Kissed Last Night",
        "Sticky Shoes",
        "Pervert Parade"
      ],
      "solution": 0,
      "cooldown": 5,
      "time": 12,
      "difficulty": 2,
      "image": "https://images.unsplash.com/photo-1574375927938-d5a98e8ffe85?w=500"
    },
    {
      "question": "What is the name of Ted's architecture firm in 'How I Met Your Mother'?",
      "answers": [
        "Goliath National Bank",
        "Mosbius Designs",
        "Barney & Associates",
        "Marshall & Lily Inc"
      ],
      "solution": 1,
      "cooldown": 5,
      "time": 15,
      "difficulty": 3,
      "image": "https://images.unsplash.com/photo-1574375927938-d5a98e8ffe85?w=500"
    },
    {
      "question": "In 'The Office', what is Michael Scott's favorite restaurant?",
      "answers": [
        "Applebee's",
        "Chili's",
        "TGI Friday's",
        "Olive Garden"
      ],
      "solution": 1,
      "cooldown": 5,
      "time": 15,
      "difficulty": 3,
      "image": "https://images.unsplash.com/photo-1574375927938-d5a98e8ffe85?w=500"
    },
    {
      "question": "What is Joey's famous pickup line in 'Friends'?",
      "answers": [
        "How you doin'?",
        "What's up?",
        "Hey there",
        "Nice to meet you"
      ],
      "solution": 0,
      "cooldown": 5,
      "time": 12,
      "difficulty": 2,
      "image": "https://images.unsplash.com/photo-1574375927938-d5a98e8ffe85?w=500"
    },
    {
      "question": "In 'Parks and Recreation', what is Leslie's favorite food?",
      "answers": [
        "Burgers",
        "Waffles",
        "Pizza",
        "Ice cream"
      ],
      "solution": 1,
      "cooldown": 5,
      "time": 12,
      "difficulty": 2,
      "image": "https://images.unsplash.com/photo-1574375927938-d5a98e8ffe85?w=500"
    },
    {
      "question": "What is Sheldon's favorite number in 'The Big Bang Theory'?",
      "answers": [
        "42",
        "73",
        "88",
        "101"
      ],
      "solution": 1,
      "cooldown": 5,
      "time": 15,
      "difficulty": 3,
      "image": "https://images.unsplash.com/photo-1574375927938-d5a98e8ffe85?w=500"
    },
    {
      "question": "In 'Brooklyn Nine-Nine', what is Jake's favorite movie?",
      "answers": [
        "Die Hard",
        "Speed",
        "Con Air",
        "Face/Off"
      ],
      "solution": 0,
      "cooldown": 5,
      "time": 15,
      "difficulty": 3,
      "image": "https://images.unsplash.com/photo-1574375927938-d5a98e8ffe85?w=500"
    },
    {
      "question": "What is the name of the documentary crew in 'The Office'?",
      "answers": [
        "PBS",
        "BBC",
        "Never mentioned",
        "Dunder Mifflin Productions"
      ],
      "solution": 2,
      "cooldown": 5,
      "time": 18,
      "difficulty": 4,
      "image": "https://images.unsplash.com/photo-1574375927938-d5a98e8ffe85?w=500"
    }
  ]
}